README.md
setup.py
MathisN_Projet_TP2.egg-info/PKG-INFO
MathisN_Projet_TP2.egg-info/SOURCES.txt
MathisN_Projet_TP2.egg-info/dependency_links.txt
MathisN_Projet_TP2.egg-info/top_level.txt
Package_Robot/Map.py
Package_Robot/__init__.py