Metadata-Version: 1.1
Name: MathisN-Projet-TP2
Version: 3.0
Summary: Crée une grille où pourra se deplacer un robot
Home-page: UNKNOWN
Author: Mathis
Author-email: mathis.nenach@cpe.fr
License: UNKNOWN
Platform: UNKNOWN
Classifier: Programming Language :: Python :: 3
